python_ft_deps/check_deps.py
python_ft_deps-0.1.1.dist-info/METADATA
python_ft_deps-0.1.1.dist-info/WHEEL
python_ft_deps-0.1.1.dist-info/entry_points.txt
python_ft_deps-0.1.1.dist-info/top_level.txt
python_ft_deps-0.1.1.dist-info/RECORD
